carlton/__init__.py
carlton/ddl/create.py
carlton/ingest/config_ingestor.py
carlton/ingest/config_validator.py
carlton/ingest/data_reader.py
carlton/ingest/data_saver.py
carlton/ingest/path_builder.py
carlton/ingest/table.py
carlton/mock/generate.py
carlton/run.py
carlton/run_notebook.py
carlton/utils/logger.py
carlton/utils/spark_session_manager.py
carlton/utils/validator.py
carlton-2.4.7.dist-info/entry_points.txt
carlton-2.4.7.dist-info/LICENSE
carlton-2.4.7.dist-info/METADATA
carlton-2.4.7.dist-info/WHEEL
carlton-2.4.7.dist-info/RECORD
