Metadata-Version: 2.1
Name: carlton
Version: 2.4.7
Summary: Carlton, uma poderosa biblioteca de ingestão de dados na cloud
License: Apache License
Author: Leal
Author-email: douglas.sleal@outlook.com
Requires-Python: >=3.10,<4.0
Classifier: Development Status :: 5 - Production/Stable
Classifier: Environment :: Console
Classifier: License :: Other/Proprietary License
Classifier: Natural Language :: Portuguese (Brazilian)
Classifier: Programming Language :: Python :: 3
Classifier: Programming Language :: Python :: 3.10
Classifier: Programming Language :: Python :: 3.11
Classifier: Programming Language :: Python :: 3.12
Classifier: Programming Language :: Python :: 3.9
Classifier: Topic :: Education
Requires-Dist: azure-eventhub (>=5.12.2,<6.0.0)
Requires-Dist: azure-identity (>=1.19.0,<2.0.0)
Requires-Dist: datacontract-cli (>=0.10.14,<0.11.0)
Project-URL: Bug Tracker, https://github.com/lealdouglas/carlton/issues
Project-URL: Código, https://github.com/lealdouglas/carlton
Project-URL: Documentação, https://carlton.readthedocs.io/pt-br/latest/
